ndnsimgraph/__init__.py
ndnsimgraph/bandwidthUtilization.py
ndnsimgraph/common.py
ndnsimgraph/delay.py
ndnsimgraph/deliveryTime.py
ndnsimgraph/drop.py
ndnsimgraph/throughput.py
ndnsimgraph-0.3.1.dist-info/LICENSE
ndnsimgraph-0.3.1.dist-info/METADATA
ndnsimgraph-0.3.1.dist-info/WHEEL
ndnsimgraph-0.3.1.dist-info/top_level.txt
ndnsimgraph-0.3.1.dist-info/RECORD
