Metadata-Version: 2.1
Name: ndnsimgraph
Version: 0.3.1
Summary: A small graph package used to draw image for ndnsim metrics
Home-page: https://github.com/SunnyQjm/ndnsim-graph
Author: SunnyQjm
Author-email: qjm253@pku.edu.cn
Classifier: Programming Language :: Python :: 3
Classifier: License :: OSI Approved :: MIT License
Classifier: Operating System :: OS Independent
License-File: LICENSE
Requires-Dist: openpyxl
Requires-Dist: matplotlib
Requires-Dist: pandas
Requires-Dist: rich
Requires-Dist: jinja2
